README.md
setup.py
django_tutu.egg-info/PKG-INFO
django_tutu.egg-info/SOURCES.txt
django_tutu.egg-info/dependency_links.txt
django_tutu.egg-info/requires.txt
django_tutu.egg-info/top_level.txt
tutu/__init__.py
tutu/admin.py
tutu/alerts.py
tutu/metrics.py
tutu/models.py
tutu/urls.py
tutu/utils.py
tutu/views.py
tutu/management/__init__.py
tutu/management/commands/__init__.py
tutu/management/commands/tutu_tick.py
tutu/migrations/0001_initial.py
tutu/migrations/0002_auto_20200121_1358.py
tutu/migrations/__init__.py